[
    {
        "DIVISION": "DIVISION",
        "TIME(HRS)": "TIME(HRS)",
        "REASON": "REASON",
        "AREA": "AREA"
    },
    {
        "DIVISION": "DARYAGANJ",
        "TIME(HRS)": "11:00-13:00",
        "REASON": "DEFECT IN OPERATION MECHANISM",
        "AREA": "LIG/MIG RES/NON COMM AREA-IPGCL-PRAGATI MAIDAN,"
    },
    {
        "DIVISION": "LAXMI NAGAR",
        "TIME(HRS)": "11:03-13:03",
        "REASON": "DEFECT IN OPERATION MECHANISM",
        "AREA": "GANESH NAGAR EXTN.-SHAKARPUR KHAS,"
    },
    {
        "DIVISION": "LAXMI NAGAR",
        "TIME(HRS)": "12:03-13:03",
        "REASON": "DEFECT IN OPERATION MECHANISM",
        "AREA": "SHAKARPUR EXTN.-SHAKARPUR KHAS,"
    },
    {
        "DIVISION": "LAXMI NAGAR",
        "TIME(HRS)": "13:03-14:03",
        "REASON": "DEFECT IN OPERATION MECHANISM",
        "AREA": "BLOCK B-KUNDAN NAGAR-LAKSHMI NAGAR,KUNDAN NAGAR-LAKSHMI NAGAR,BANK ENCLAVE-LAKSHMI NAGAR,BLOCK B-PRIYADARSANI VIHAR-LAKSHMI NAGAR,"
    },
    {
        "DIVISION": "KARAWAL NAGAR",
        "TIME(HRS)": "11:03-14:03",
        "REASON": "NETWORK UPGRADATION",
        "AREA": "C BLOCK-BRIJ PURI-GOKULPURI,"
    },
    {
        "DIVISION": "KARAWAL NAGAR",
        "TIME(HRS)": "11:03-14:03",
        "REASON": "NETWORK UPGRADATION",
        "AREA": "G & H BLOCK-OLD MUSTAFABAD-GOKULPURI,D BLOCK-DAYALPUR-GALI 3 & 4,D BLOCK-DAYALPUR-SONIA VIHAR,"
    },
    {
        "DIVISION": "KRISHNA NAGAR",
        "TIME(HRS)": "11:03-13:03",
        "REASON": "NETWORK UPGRADATION",
        "AREA": "NEW LAHORE EXTENTION-JJ COLONY-GEETA COLONY,RANI GARDEN-GEETA COLONY,RANI GARDEN-JJ COLONY-GEETA COLONY,RANI GARDEN-SUNDER PARK-GEETA COLONY,"
    },
    {
        "DIVISION": "YAMUNA VIHAR",
        "TIME(HRS)": "11:03-13:03",
        "REASON": "NETWORK UPGRADATION",
        "AREA": "BLOCK F- LIG/MIG RES/NON COMM AREA-NEW SILAMPURI PHASE II,"
    },
    {
        "DIVISION": "SHANKAR ROAD",
        "TIME(HRS)": "11:00-13:00",
        "REASON": "NETWORK UPGRADATION",
        "AREA": "BLOCK_37J-BEADON PURA-KAROL BAGH,BLOCK 29-NAIWALA-KAROL BAGH,BLOCK T-ASHOKA PAHARI-JHANDEWALAN,MOHALLA SUBHASH NAGAR-NAIWALA-KAROL BAGH,BLOCK_25K-BEADON PURA-KAROL BAGH,"
    },
    {
        "DIVISION": "SHANKAR ROAD",
        "TIME(HRS)": "11:00-14:00",
        "REASON": "NETWORK UPGRADATION",
        "AREA": "BLOCK_3H-KRISHNA NAGAR-KAROL BAGH,BLOCK_19C-KRISHNA NAGAR-KAROL BAGH,"
    },
    {
        "DIVISION": "KARKARDOOMA",
        "TIME(HRS)": "10:00-12:00",
        "REASON": "NETWORK UPGRADATION WORK",
        "AREA": "MAHARAM NAGAR-SHAHDARA,SUNDER PARK-SHAHDARA,EAST ROHTASH NAGAR-SHAHDARA,"
    },
    {
        "DIVISION": "DARYAGANJ",
        "TIME(HRS)": "11:30-13:30",
        "REASON": "NETWORK UPGRADATION",
        "AREA": "CHANDANI MAHAL-CHANDNI CHOWK,"
    },
    {
        "DIVISION": "GT ROAD",
        "TIME(HRS)": "10:00-13:00",
        "REASON": "NETWORK UPGRADATION WORK",
        "AREA": "PETROL PUMP-JULFE BENGAL INDUSTRIAL AREA-DILSHAD GARDEN,OBERAI COMPOUND-DILSHAD GARDEN,LIG/MIG RES/NON COMM AREA-LIC COLONY DILSHAD GARDEN,SIDDHARTH INTER NATIONAL SCHOOL-POCKET B-DILSHAD GARDEN,THE BOILER COMPONENTS S M F G COMPANY-POCKET B-DILSHAD GARDEN,LIG FLATS-POCKET F & E-DILSHAD GARDEN,LIG/MIG RES/NON COMM AREA-KALANDER COLONY-DILSHAD GARDEN,R.B PUBLIC SCHOOL-KALANDER COLONY-DILSHAD GARDEN,BLOCK E- INDUSTRIAL FACTORY-ARWACHIN INTERNATIONAL SCHOOL-DILSHAD GARDEN,JHUALI JOHOPARI (J J C)-ARWACHIN INTERNATIONAL SCHOOL-DILSHAD GARDEN,GURUDWARA-ARWACHIN INTERNATIONAL SCHOOL-DILSHAD GARDEN,"
    },
    {
        "DIVISION": "KRISHNA NAGAR",
        "TIME(HRS)": "10:00-13:00",
        "REASON": "NETWORK UPGRADATION WORK",
        "AREA": "NEW GOVIND PURA-JAGATPURI,BALDEV PARK-JAGATPURI,"
    },
    {
        "DIVISION": "KARKARDOOMA",
        "TIME(HRS)": "10:30-12:30",
        "REASON": "CIVIL WORK",
        "AREA": "AMBEDKAR NAGAR-SHAHDARA,JAWALA NAGAR-SHAHDARA,"
    },
    {
        "DIVISION": "PATEL NAGAR",
        "TIME(HRS)": "10:30-13:30",
        "REASON": "CIVIL WORK",
        "AREA": "MIG FLATS-PRASAD NAGAR-KAROL BAGH,ST.MICHAELS JUNIOR SCHOOL-PRASAD NAGAR-KAROL BAGH,DEPARTMENT OF TELECOMMUNICATIONS-PRASAD NAGAR-KAROL BAGH,"
    },
    {
        "DIVISION": "PATEL NAGAR",
        "TIME(HRS)": "11:00-13:00",
        "REASON": "TO ATTEND PIERCING CONNECTOR BURNT DAMAGE",
        "AREA": "PREM NAGAR-BALJIT NAGAR,"
    },
    {
        "DIVISION": "KARKARDOOMA",
        "TIME(HRS)": "11:00-14:00",
        "REASON": "TRANSFORMER REPLACEMENT",
        "AREA": "SUNDER PARK-SHAHDARA,"
    },
    {
        "DIVISION": "YAMUNA VIHAR",
        "TIME(HRS)": "11:00-13:00",
        "REASON": "RMU REPLACEMENT",
        "AREA": "BLOCK J-SILAMPUR COLONY,"
    },
    {
        "DIVISION": "KARAWAL NAGAR",
        "TIME(HRS)": "11:00-14:00",
        "REASON": "NETWORK UPGRADATION WORK",
        "AREA": "E-2 BLOCK-SHIVAJI MOHALLA-SONIA VIHAR,G4 & G5 BLOCK-PUSTA 5 -RAM KRISHAN MOHALLA-NEAR KVC BUILDER,G1 & G2-BLOCK-PUSTA-5-RAM RATAN SCHOOL,G4 & G5 BLOCK-PUSTA -5-SONIA VIHAR EXTENSION,"
    },
    {
        "DIVISION": "GT ROAD",
        "TIME(HRS)": "11:00-13:00",
        "REASON": "CIVIL WORK",
        "AREA": "POST OFFICE-DILSHAD GARDEN,FACTORY-DILSHAD GARDEN,DELHI JAL BOARD-C BLOCK DILSHAD GARDEN,"
    },
    {
        "DIVISION": "KARAWAL NAGAR",
        "TIME(HRS)": "11:00-13:00",
        "REASON": "NETWORK UPGRADATION WORK",
        "AREA": "N & M-BLOCK-SADATPUR EXT,C-5-SADAT PUR,L-BLOCK-SADATPUR-SONIA VIHAR,K-BLOCK-GALI-51-SADATPUR EXT,L-BLOCK-SADAT PUR,"
    },
    {
        "DIVISION": "GT ROAD",
        "TIME(HRS)": "11:00-13:00",
        "REASON": "TO CONNECT NEW CABLE",
        "AREA": "BLOCK E-OLD SIMAPURI-DILSHAD GARDEN,BLOCK C-OLD SIMAPURI-DILSHAD GARDEN,BLOCK B-OLD SIMAPURI-DILSHAD GARDEN,GOVT. DISPENCERY-OLD SIMAPURI-DILSHAD GARDEN,"
    },
    {
        "DIVISION": "KARAWAL NAGAR",
        "TIME(HRS)": "11:00-14:00",
        "REASON": "NETWORK UPGRADATION WORK",
        "AREA": "PKT B-BLOCK B-SADAT PUR,PKT A-BLOCK E-SADAT PUR,PKT C-BLOCK E-SADAT PUR,PKT A1-BLOCK E-SADAT PUR,PKT A4-BLOCK E-SADAT PUR,BLOCK D-WEST KARAWAL NAGAR,GALI NO. 8 TO 16-DAYALPUR,D-BLOCK-NEAR JEEVAN JYOTI SCHOOL-SADATPUR EXT.,K-BLOCK-SADATPUR EXT--SONIA VIHAR,"
    },
    {
        "DIVISION": "GT ROAD",
        "TIME(HRS)": "11:00-13:00",
        "REASON": "NETWORK UPGRADATION WORK",
        "AREA": "BLOCK A-DILSHAD COLONY-DILSHAD GARDEN,BLOCK F-DILSHAD COLONY-DILSHAD GARDEN,BLOCK B-DILSHAD COLONY-DILSHAD GARDEN,J.J.C.-NEW SIMAPURI-DILSHAD GARDEN,BLOCK B-NEW SIMAPURI-DILSHAD GARDEN,BLOCK C-NEW SIMAPURI-DILSHAD GARDEN,"
    },
    {
        "DIVISION": "NAND NAGRI",
        "TIME(HRS)": "11:03-14:03",
        "REASON": "REPLACEMENT OF HVDS TRANSFORMER",
        "AREA": "BLOCK E-RAJIV NAGAR-MANDOLI,"
    },
    {
        "DIVISION": "NAND NAGRI",
        "TIME(HRS)": "11:03-14:03",
        "REASON": "NETWORK UPGRADATION WORK",
        "AREA": "SABOLI COLONY-MANDOLI,SABOLI VILLAGE-MANDOLI,BLOCK B-RADHA VIHAR-MANDOLI,BLOCK C-A-3-HARSH VIHAR-MANDOLI,BLOCK D-VILLAGE SABOLI-MANDOLI,BLOCK K-VILLAGE SABOLI-MANDOLI,BLOCK A-VILLAGE SABOLI-MANDOLI,BLOCK C-PRATAP NAGAR- RADHA VIHAR-MANDOLI,PRATAP NAGAR- RADHA VIHAR-MANDOLI,BLOCK B-SHAKTI GARDEN,BLOCK A-EAST GOKUL PUR,"
    },
    {
        "DIVISION": "KARAWAL NAGAR",
        "TIME(HRS)": "09:30-12:30",
        "REASON": "SYSTEM IMPROVEMENT WORK",
        "AREA": "D BLOCK-BRIJ PURI-GOKULPURI,"
    },
    {
        "DIVISION": "GT ROAD",
        "TIME(HRS)": "10:00-12:30",
        "REASON": "SYSTEM IMPROVEMENT WORK",
        "AREA": "INDIRA CAMP-A BLOCK JHILMIL INDUSTRIAL AREA,JHILMIL INDUSTRIAL AREA BLOCK A-A BLOCK JHILMIL INDUSTRIAL AREA,"
    },
    {
        "DIVISION": "NAND NAGRI",
        "TIME(HRS)": "10:00-12:30",
        "REASON": "SYSTEM IMPROVEMENT WORK",
        "AREA": "BABARPUR WEST-BABAR PUR,CHHAJJUPUR-BABAR PUR,BABARPUR EXTN.-BABAR PUR,BALBIR NAGAR EXTN.,"
    },
    {
        "DIVISION": "LAXMI NAGAR",
        "TIME(HRS)": "11:03-14:03",
        "REASON": "TRANSFORMER REPLACEMENT",
        "AREA": "GANESH NAGAR-SHAKARPUR KHAS,BLOCK WA&O-SHAKARPUR KHAS,BLOCK S-SHAKARPUR KHAS,"
    },
    {
        "DIVISION": "YAMUNA VIHAR",
        "TIME(HRS)": "10:00-13:00",
        "REASON": "SYSTEM IMPROVEMENT WORK",
        "AREA": "BLOCK B-NEW SILAMPURI PHASE II,BLOCK E-NEW SILAMPURI PHASE II,BLOCK F- LIG/MIG RES/NON COMM AREA-NEW SILAMPURI PHASE II,BLOCK D- LIG/MIG RES/NON COMM AREA-NEW SILAMPURI PHASE II,"
    },
    {
        "DIVISION": "KARKARDOOMA",
        "TIME(HRS)": "11:03-13:03",
        "REASON": "REPLACEMENT/ REPAIR OF RMU",
        "AREA": "BLOCK B-SURAJMAL VIHAR-VIVEK VIHAR,"
    },
    {
        "DIVISION": "CHANDNI CHOWK",
        "TIME(HRS)": "11:03-13:03",
        "REASON": "RELAY REPLACEMEMT",
        "AREA": "BALI MARAN-BARA DARI-CHANDNI CHOWK,KATRA BARYAN-BARA DARI-CHANDNI CHOWK,"
    },
    {
        "DIVISION": "NAND NAGRI",
        "TIME(HRS)": "10:00-13:00",
        "REASON": "SYSTEM IMPROVEMENT WORK",
        "AREA": "BLOCK E-RAJIV NAGAR-MANDOLI,NEW MANDOLI INDUSTRIAL AREA,DEEPAK MEDITECH-NEW MANDOLI INDUSTRIAL AREA,BLOCK A-RAJIV NAGAR-MANDOLI,"
    },
    {
        "DIVISION": "KRISHNA NAGAR",
        "TIME(HRS)": "10:00-13:00",
        "REASON": "SYSTEM IMPROVEMENT WORK",
        "AREA": "CHANDER NAGAR BLOCK D-SHASTRI PARK-KRISHNA NAGAR,CHANDER NAGAR BLOCK D-KRISHNA NAGAR EXTN.,"
    },
    {
        "DIVISION": "LAXMI NAGAR",
        "TIME(HRS)": "11:03-14:03",
        "REASON": "TRANSFORMER REPLACEMENT",
        "AREA": "BLOCK G-LAKSHMI NAGAR,BLOCK D-LALITA PARK-LAKSHMI NAGAR,LAKSHMI NAGAR BLOCK L,BLOCK F-LALITA PARK-LAKSHMI NAGAR,BLOCK K-JAGAT RAM PARK-LAKSHMI NAGAR,"
    },
    {
        "DIVISION": "GT ROAD",
        "TIME(HRS)": "10:00-12:30",
        "REASON": "SYSTEM IMPROVEMENT WORK",
        "AREA": "FRIENDS COLONY INDUSTRIAL AREA,"
    },
    {
        "DIVISION": "KRISHNA NAGAR",
        "TIME(HRS)": "11:30-13:30",
        "REASON": "RMU REPLACEMENT",
        "AREA": "BLOCK C-RADHEPURI EXTENSION-KRISHNA NAGAR,BLOCK E-RADHEPURI EXTENSION-KRISHNA NAGAR,RADHEY PURI EXTENSION-ARJUN NAGAR WEST-KRISHNA NAGAR,KRISHNA NAGAR EAST BLOCK E-RADHEPURI,"
    },
    {
        "DIVISION": "YAMUNA VIHAR",
        "TIME(HRS)": "12:00-14:00",
        "REASON": "NETWORK UPGRADATION WORK",
        "AREA": "BLOCK B-SUBHASH MOHALLA-BHAJANPURA,VIJAY PARK-YAMUNA VIHAR,SUBHASH VIHAR-YAMUNA VIHAR,MAUJ PUR COMPLEX 1,NORTH GHONDA,BSES 66 KV GRID S/STATION-COMMUNITY CENTRE YAMUNA VIHAR,"
    },
    {
        "DIVISION": "SHANKAR ROAD",
        "TIME(HRS)": "10:00-12:30",
        "REASON": "SYSTEM IMPROVEMENT WORK",
        "AREA": "BLOCK_1A-REHAGAR PURA-KAROL BAGH,BLOCK_1A-REHAGAR PURA-KAROL BAGH,"
    },
    {
        "DIVISION": "MAYUR VIHAR I AND II",
        "TIME(HRS)": "12:03-14:03",
        "REASON": "TO CONNECT NEW CABLE",
        "AREA": "TRILOKPURI PHASE I-MAYUR VIHAR,"
    },
    {
        "DIVISION": "VASUNDHARA ENCLAVE",
        "TIME(HRS)": "12:03-14:03",
        "REASON": "NETWORK UPGRADTION WORK",
        "AREA": "BLOCK B-KONDALI EXTN.-GHAROLI KONDLI,KONDALI VILLAGE-GHAROLI KONDLI,SEC D-MAYUR VIHAR PHASE III,BLOCK B-KONDALI VILLAGE-GHAROLI KONDLI,BLOCK A-KONDALI VILLAGE-GHAROLI KONDLI,BLOCK E-KONDALI VILLAGE-GHAROLI KONDLI,BLOCK C-KONDALI VILLAGE-GHAROLI KONDLI,BLOCK F-KONDALI VILLAGE-GHAROLI KONDLI,"
    },
    {
        "DIVISION": "MAYUR VIHAR I AND II",
        "TIME(HRS)": "12:03-14:03",
        "REASON": "NETWORK UPGRADTION WORK",
        "AREA": "KHICHARIPUR-GAZIPUR,BLOCK 7-KHICHRIPUR RESETTLEMENT COLONY BLOCK 7-KHICHARIPUR,BLOCK 8-KHICHRIPUR RESETTLEMENT COLONY BLOCK 8-KHICHARIPUR,"
    },
    {
        "DIVISION": "KARKARDOOMA",
        "TIME(HRS)": "10:00-13:00",
        "REASON": "SYSTEM IMPROVEMENT WORK",
        "AREA": "GOVIND KHAND-JHILMIL COLONY,JHILMIL COLONY BLOCK B,"
    },
    {
        "DIVISION": "NAND NAGRI",
        "TIME(HRS)": "14:03-17:03",
        "REASON": "RMU REPLACEMENT",
        "AREA": "HARSH VIHAR SUB STATION-POLICE FARM HOUSE-MANDOLI,BLOCK C-RAJEEV NAGAR-MANDOLI,BLOCK B-HARSH VIHAR-MANDOLI,BLOCK A-HARSH VIHAR-MANDOLI,TUKMIRPUR VILLAGE-SONIA VIHAR,B & C-BLOCK-SHRI RAM COLONY-RAJEEV NAGAR,BIHARIPUR EXT-NEAR CRPF CAMP-SONIA VIHAR,A-BLOCK-ZERO PUSTA-0 PUSTA POCKET-1,A BLOCK PART-3-POCKET-3-PUSTA-1,"
    },
    {
        "DIVISION": "CHANDNI CHOWK",
        "TIME(HRS)": "14:03-16:03",
        "REASON": "RELAY REPLACEMEMT",
        "AREA": "MAIN MARKET-KATRA DHOBI-MORI GATE,TIS HAZARI SADAR BAZAR-RAJENDRA MARKET-MORI GATE,OLD DELHI RAILWAY STATION-CHANDNI CHOWK,"
    },
    {
        "DIVISION": "DARYAGANJ",
        "TIME(HRS)": "10:03-13:03",
        "REASON": "SYSTEM IMPROVEMENT WORK",
        "AREA": "KAMLA MARKET-AJMERI GATE,U.P.ROADWAYS BUS STANDS-PAHAR GANJ DRG,SMT. GIRDHARI LAL C.D. PRASUTI HOSPITAL-KAMLA MARKET-AJMERI GATE,"
    },
    {
        "DIVISION": "MAYUR VIHAR I AND II",
        "TIME(HRS)": "10:03-12:33",
        "REASON": "SYSTEM IMPROVEMENT WORK",
        "AREA": "PHASE I-MAYUR VIHAR,"
    },
    {
        "DIVISION": "NAND NAGRI",
        "TIME(HRS)": "10:03-12:33",
        "REASON": "SYSTEM IMPROVEMENT WORK",
        "AREA": "GTB MIG FLATS-POCKET F-GURU TEG BAHADUR ENCLAVE,"
    },
    {
        "DIVISION": "MAYUR VIHAR I AND II",
        "TIME(HRS)": "10:15-13:15",
        "REASON": "SYSTEM IMPROVEMENT WORK",
        "AREA": "GAZIPUR DAIRY FARM,"
    },
    {
        "DIVISION": "PAHARGANJ",
        "TIME(HRS)": "10:30-13:00",
        "REASON": "SYSTEM IMPROVEMENT WORK",
        "AREA": "SHEELA HOTEL-ARYA NAGAR-SADAR BAZAR,"
    },
    {
        "DIVISION": "CHANDNI CHOWK",
        "TIME(HRS)": "10:30-13:30",
        "REASON": "SYSTEM IMPROVEMENT WORK",
        "AREA": "BALI MARAN-BARA DARI-CHANDNI CHOWK,FATEHPURI-KUCHA HASIRAM-CHANDNI CHOWK,"
    },
    {
        "DIVISION": "YAMUNA VIHAR",
        "TIME(HRS)": "10:30-13:30",
        "REASON": "SYSTEM IMPROVEMENT WORK",
        "AREA": "SUBHASH PARK-GORAKH PARK-SILAMPUR,"
    },
    {
        "DIVISION": "PATEL NAGAR",
        "TIME(HRS)": "10:30-13:30",
        "REASON": "SYSTEM IMPROVEMENT WORK",
        "AREA": "BLOCK F-PUNJABI BASTI-PREM NAGAR (NEHRU NAGAR),PREM NAGAR-BALJIT NAGAR,CHETAN BASTI- BLOCK J-NEHRU NAGAR,"
    },
    {
        "DIVISION": "MAYUR VIHAR I AND II",
        "TIME(HRS)": "10:30-13:00",
        "REASON": "SYSTEM IMPROVEMENT WORK",
        "AREA": "CL-CHILLA SARDA BANGAR VILLAGE-MAYUR VIHAR,MAYUR VIHAR EXTN.,"
    },
    {
        "DIVISION": "VASUNDHARA ENCLAVE",
        "TIME(HRS)": "10:30-13:00",
        "REASON": "SYSTEM IMPROVEMENT WORK",
        "AREA": "BLOCK_G1/A-KONDALI GHAROLI SECTOR G-GHAROLI KONDLI,BLOCK_G2/B-KONDALI GHAROLI SECTOR G-GHAROLI KONDLI,"
    },
    {
        "DIVISION": "KARKARDOOMA",
        "TIME(HRS)": "11:00-14:00",
        "REASON": "SYSTEM IMPROVEMENT WORK",
        "AREA": "SUNDER PARK-SHAHDARA,BHOLA NATH NAGAR-SHAHDARA,TELIBARA-SHAHDARA,MAHARAM NAGAR-SHAHDARA,BIHARI COLONY-SHAHDARA,SHALIMAR PARK-SHAHDARA,EAST ROHTASH NAGAR-SHAHDARA,"
    },
    {
        "DIVISION": "DARYAGANJ",
        "TIME(HRS)": "11:00-13:30",
        "REASON": "SYSTEM IMPROVEMENT WORK",
        "AREA": "MINISTRY OF COMMUNICATION-ROUSE AVENUE-AJMERI GATE,MEDICAL COUNCIL OF INDIA-BAL BHAWAN-AJMERI GATE,INDRAPRASTH HEAD POST OFFICE-ITO-AJMERI GATE,"
    },
    {
        "DIVISION": "LAXMI NAGAR",
        "TIME(HRS)": "11:01-14:01",
        "REASON": "SYSTEM IMPROVEMENT WORK",
        "AREA": "EAST END ENCLAVE-LAKSHMI NAGAR,MOHAN PARK-WEST GURU ANGAD NAGAR-LAKSHMI NAGAR,GURU ANGAD NAGAR EAST-SWASTHYA VIHAR-LAKSHMI NAGAR,LAXMI NAGAR COMMERCIAL COPLEX-SWASTHYA VIHAR-LAKSHMI NAGAR,"
    },
    {
        "DIVISION": "LAXMI NAGAR",
        "TIME(HRS)": "11:03-14:03",
        "REASON": "SYSTEM IMPROVEMENT WORK",
        "AREA": "PRIYADARSHINI APARTMENT-MOTHER DAIRY-INDRAPRASTHA EXTENSION LNR,"
    },
    {
        "DIVISION": "PAHARGANJ",
        "TIME(HRS)": "11:00-13:00",
        "REASON": "PROJECT WORK",
        "AREA": "BLOCK T-AHATA KEDARA-SADAR BAZAR,"
    },
    {
        "DIVISION": "GT ROAD",
        "TIME(HRS)": "11:00-13:00",
        "REASON": "PROJECT WORK",
        "AREA": "BLOCK B-NEW SIMAPURI-DILSHAD GARDEN,J.J.C.-NEW SIMAPURI-DILSHAD GARDEN,BLOCK C-NEW SIMAPURI-DILSHAD GARDEN,"
    },
    {
        "DIVISION": "PAHARGANJ",
        "TIME(HRS)": "11:00-13:00",
        "REASON": "PROJECT WORK",
        "AREA": "TELI WARA-NAWAB GANJ-SADAR BAZAR,"
    },
    {
        "DIVISION": "YAMUNA VIHAR",
        "TIME(HRS)": "11:03-13:03",
        "REASON": "PROJECT WORK",
        "AREA": "NAYAGAON-NEW KATWARA-USMAN PUR,NEW USMANPUR-NEW KATWARA-USMAN PUR,"
    },
    {
        "DIVISION": "SHANKAR ROAD",
        "TIME(HRS)": "11:00-13:00",
        "REASON": "SYSTEM IMPROVEMENT WORK",
        "AREA": "BLOCK_19C-KRISHNA NAGAR-KAROL BAGH,BLOCK_20C-KRISHNA NAGAR-KAROL BAGH,BLOCK_3H-KRISHNA NAGAR-KAROL BAGH,BLOCK_21K-KRISHNA NAGAR-KAROL BAGH,BLOCK_30B-KRISHNA NAGAR-KAROL BAGH,"
    }
]