[
    {
        "country": "India",
        "start": "2025-03-17_11-00-00",
        "end": "2025-03-17_14-00-00",
        "duration_(hours)": 3,
        "event_category": "maintenance schedule",
        "area_affected": {
            "CHHATARPUR": [
                "11KV FDR NICF VIA AYA NAGA"
            ]
        }
    },
    {
        "country": "India",
        "start": "2025-03-17_11-00-00",
        "end": "2025-03-17_14-00-00",
        "duration_(hours)": 3,
        "event_category": "maintenance schedule",
        "area_affected": {
            "SAKET": [
                "11KV FDR O/G MALVIYA NGR. HOSPITA"
            ]
        }
    },
    {
        "country": "India",
        "start": "2025-03-17_11-00-00",
        "end": "2025-03-17_14-00-00",
        "duration_(hours)": 3,
        "event_category": "maintenance schedule",
        "area_affected": {
            "CHHATARPUR": [
                "11KV FDR O/G TO M.C TR. DLF (MEHAR CHAND"
            ]
        }
    },
    {
        "country": "India",
        "start": "2025-03-17_11-00-00",
        "end": "2025-03-17_14-00-00",
        "duration_(hours)": 3,
        "event_category": "maintenance schedule",
        "area_affected": {
            "R K PURAM": [
                "11KV FDR O/G R.K PURAM SECTOR-"
            ]
        }
    },
    {
        "country": "India",
        "start": "2025-03-17_11-00-00",
        "end": "2025-03-17_14-00-00",
        "duration_(hours)": 3,
        "event_category": "maintenance schedule",
        "area_affected": {
            "CHHATARPUR": [
                "11KV FDR O/G ASHWANI KUMAR MEHRA HOTE"
            ]
        }
    },
    {
        "country": "India",
        "start": "2025-03-17_11-00-00",
        "end": "2025-03-17_14-00-00",
        "duration_(hours)": 3,
        "event_category": "maintenance schedule",
        "area_affected": {
            "NAJAFGARH": [
                "11KV FDR PRASHANT SS-BD CW"
            ]
        }
    },
    {
        "country": "India",
        "start": "2025-03-17_11-00-00",
        "end": "2025-03-17_14-00-00",
        "duration_(hours)": 3,
        "event_category": "maintenance schedule",
        "area_affected": {
            "HAUZ KHAS": [
                "11KV FDR O/G TIFAC BUILDIN"
            ]
        }
    },
    {
        "country": "India",
        "start": "2025-03-17_11-00-00",
        "end": "2025-03-17_14-00-00",
        "duration_(hours)": 3,
        "event_category": "maintenance schedule",
        "area_affected": {
            "NIZAMUDDIN": [
                "11KV FDR LODHI COLONEY COMP. CENTE"
            ]
        }
    },
    {
        "country": "India",
        "start": "2025-03-17_11-00-00",
        "end": "2025-03-17_14-00-00",
        "duration_(hours)": 3,
        "event_category": "maintenance schedule",
        "area_affected": {
            "CHHATARPUR": [
                "11KV FDR OG TO G BLK AYA NAGA"
            ]
        }
    },
    {
        "country": "India",
        "start": "2025-03-17_11-00-00",
        "end": "2025-03-17_14-00-00",
        "duration_(hours)": 3,
        "event_category": "maintenance schedule",
        "area_affected": {
            "UTTAM NAGAR": [
                "11KV FDR CHANAKYA PLAC"
            ]
        }
    },
    {
        "country": "India",
        "start": "2025-03-17_11-00-00",
        "end": "2025-03-17_14-00-00",
        "duration_(hours)": 3,
        "event_category": "maintenance schedule",
        "area_affected": {
            "NANGLOI": [
                "11KV FDR S/STN NO\u22121 MIANWALI NAGA"
            ]
        }
    },
    {
        "country": "India",
        "start": "2025-03-17_11-00-00",
        "end": "2025-03-17_13-00-00",
        "duration_(hours)": 2,
        "event_category": "maintenance schedule",
        "area_affected": {
            "NEW FRIENDS COLONY": [
                "11KV FDR OKHLA FILTERATION PLAN"
            ]
        }
    },
    {
        "country": "India",
        "start": "2025-03-17_11-00-00",
        "end": "2025-03-17_14-00-00",
        "duration_(hours)": 3,
        "event_category": "maintenance schedule",
        "area_affected": {
            "PUNJABI BAGH": [
                "11KV FDR A F O (DIST EAST PUNJABI BAGH"
            ]
        }
    },
    {
        "country": "India",
        "start": "2025-03-17_11-00-00",
        "end": "2025-03-17_14-00-00",
        "duration_(hours)": 3,
        "event_category": "maintenance schedule",
        "area_affected": {
            "NEW FRIENDS COLONY": [
                "11KV FDR B-BLOCK F.COLON"
            ]
        }
    },
    {
        "country": "India",
        "start": "2025-03-17_11-00-00",
        "end": "2025-03-17_14-00-00",
        "duration_(hours)": 3,
        "event_category": "maintenance schedule",
        "area_affected": {
            "CHHATARPUR": [
                "11KV FDR O/G TO ASOLA VILLAG"
            ]
        }
    },
    {
        "country": "India",
        "start": "2025-03-17_11-00-00",
        "end": "2025-03-17_14-00-00",
        "duration_(hours)": 3,
        "event_category": "maintenance schedule",
        "area_affected": {
            "NEHRU PLACE": [
                "11KV FDR E\u2212BLOCK (K) S/STN. G.K-"
            ]
        }
    },
    {
        "country": "India",
        "start": "2025-03-17_11-00-00",
        "end": "2025-03-17_14-00-00",
        "duration_(hours)": 3,
        "event_category": "maintenance schedule",
        "area_affected": {
            "PALAM": [
                "11KV FDR SARGODHA VIHAR SEC-7 (PLM"
            ]
        }
    },
    {
        "country": "India",
        "start": "2025-03-17_11-00-00",
        "end": "2025-03-17_14-00-00",
        "duration_(hours)": 3,
        "event_category": "maintenance schedule",
        "area_affected": {
            "JANAKPURI": [
                "11KV FDR C-4 DABR"
            ]
        }
    },
    {
        "country": "India",
        "start": "2025-03-17_11-00-00",
        "end": "2025-03-17_14-00-00",
        "duration_(hours)": 3,
        "event_category": "maintenance schedule",
        "area_affected": {
            "SARITA VIHAR": [
                "11KV FDR O/G 4-POLE POLICE STATIO"
            ]
        }
    },
    {
        "country": "India",
        "start": "2025-03-17_11-00-00",
        "end": "2025-03-17_14-00-00",
        "duration_(hours)": 3,
        "event_category": "maintenance schedule",
        "area_affected": {
            "PALAM": [
                "11KV FDR N.B.E. SEC.-"
            ]
        }
    },
    {
        "country": "India",
        "start": "2025-03-17_11-00-00",
        "end": "2025-03-17_14-00-00",
        "duration_(hours)": 3,
        "event_category": "maintenance schedule",
        "area_affected": {
            "TAGORE GARDEN": [
                "11KV FDR AB-BLOCK KHYAL"
            ]
        }
    },
    {
        "country": "India",
        "start": "2025-03-17_11-00-00",
        "end": "2025-03-17_14-00-00",
        "duration_(hours)": 3,
        "event_category": "maintenance schedule",
        "area_affected": {
            "UTTAM NAGAR": [
                "11KV FDR SANJAY ENCLAV"
            ]
        }
    },
    {
        "country": "India",
        "start": "2025-03-17_11-00-00",
        "end": "2025-03-17_14-00-00",
        "duration_(hours)": 3,
        "event_category": "maintenance schedule",
        "area_affected": {
            "KHANPUR": [
                "11KV FDR TIGRI J.J KHANPU"
            ]
        }
    },
    {
        "country": "India",
        "start": "2025-03-17_11-00-00",
        "end": "2025-03-17_14-00-00",
        "duration_(hours)": 3,
        "event_category": "maintenance schedule",
        "area_affected": {
            "HAUZ KHAS": [
                "11KV FDR O/G C-17 PANCH SHEEL PARK (RMU) NEAR FLY OVE"
            ]
        }
    },
    {
        "country": "India",
        "start": "2025-03-17_11-00-00",
        "end": "2025-03-17_14-00-00",
        "duration_(hours)": 3,
        "event_category": "maintenance schedule",
        "area_affected": {
            "VIKASPURI": [
                "11KV FDR LIG MOTHER DAIR"
            ]
        }
    },
    {
        "country": "India",
        "start": "2025-03-17_11-00-00",
        "end": "2025-03-17_14-00-00",
        "duration_(hours)": 3,
        "event_category": "maintenance schedule",
        "area_affected": {
            "NANGLOI": [
                "11KV FDR CHANDER VIHA"
            ]
        }
    },
    {
        "country": "India",
        "start": "2025-03-17_11-00-00",
        "end": "2025-03-17_14-00-00",
        "duration_(hours)": 3,
        "event_category": "maintenance schedule",
        "area_affected": {
            "SAKET": [
                "11KV FDR JAHAPANAH NO.-1 + MGF MALL VIA RMU NEAR GAT"
            ]
        }
    },
    {
        "country": "India",
        "start": "2025-03-17_11-00-00",
        "end": "2025-03-17_14-00-00",
        "duration_(hours)": 3,
        "event_category": "maintenance schedule",
        "area_affected": {
            "MOHAN GARDEN": [
                "11KV FDR DEFENCE ENCLAV"
            ]
        }
    },
    {
        "country": "India",
        "start": "2025-03-17_11-00-00",
        "end": "2025-03-17_14-00-00",
        "duration_(hours)": 3,
        "event_category": "maintenance schedule",
        "area_affected": {
            "VASANT KUNJ": [
                "11KV FDR SECTOR B-4 VASANT KUN"
            ]
        }
    },
    {
        "country": "India",
        "start": "2025-03-17_11-00-00",
        "end": "2025-03-17_14-00-00",
        "duration_(hours)": 3,
        "event_category": "maintenance schedule",
        "area_affected": {
            "NAJAFGARH": [
                "11KV FDR DTL COLON"
            ]
        }
    },
    {
        "country": "India",
        "start": "2025-03-17_11-00-00",
        "end": "2025-03-17_14-00-00",
        "duration_(hours)": 3,
        "event_category": "maintenance schedule",
        "area_affected": {
            "SARITA VIHAR": [
                "11KV FDR S/S NO.-21",
                " SARITA VIHA"
            ]
        }
    },
    {
        "country": "India",
        "start": "2025-03-17_11-00-00",
        "end": "2025-03-17_14-00-00",
        "duration_(hours)": 3,
        "event_category": "maintenance schedule",
        "area_affected": {
            "NAJAFGARH": [
                "11KV FDR ANAJ MAND"
            ]
        }
    },
    {
        "country": "India",
        "start": "2025-03-17_11-00-00",
        "end": "2025-03-17_14-00-00",
        "duration_(hours)": 3,
        "event_category": "maintenance schedule",
        "area_affected": {
            "ALAKNANDA": [
                "11KV FDR O/G C.R PARK-A",
                " S/STN-"
            ]
        }
    },
    {
        "country": "India",
        "start": "2025-03-17_11-00-00",
        "end": "2025-03-17_14-00-00",
        "duration_(hours)": 3,
        "event_category": "maintenance schedule",
        "area_affected": {
            "NANGLOI": [
                "11KV FDR AMBEDKAR CHOW"
            ]
        }
    },
    {
        "country": "India",
        "start": "2025-03-17_11-00-00",
        "end": "2025-03-17_14-00-00",
        "duration_(hours)": 3,
        "event_category": "maintenance schedule",
        "area_affected": {
            "VASANT KUNJ": [
                "11KV FDR S.P."
            ]
        }
    },
    {
        "country": "India",
        "start": "2025-03-17_11-00-00",
        "end": "2025-03-17_14-00-00",
        "duration_(hours)": 3,
        "event_category": "maintenance schedule",
        "area_affected": {
            "PALAM": [
                "11KV FDR GALI NO-22 SADH NAGA"
            ]
        }
    },
    {
        "country": "India",
        "start": "2025-03-17_11-00-00",
        "end": "2025-03-17_14-00-00",
        "duration_(hours)": 3,
        "event_category": "maintenance schedule",
        "area_affected": {
            "JANAKPURI": [
                "11KV FDR ISSAPU"
            ]
        }
    },
    {
        "country": "India",
        "start": "2025-03-17_11-00-00",
        "end": "2025-03-17_14-00-00",
        "duration_(hours)": 3,
        "event_category": "maintenance schedule",
        "area_affected": {
            "HAUZ KHAS": [
                "11KV FDR B-5",
                " S.J ENCLAV"
            ]
        }
    },
    {
        "country": "India",
        "start": "2025-03-17_11-00-00",
        "end": "2025-03-17_14-00-00",
        "duration_(hours)": 3,
        "event_category": "maintenance schedule",
        "area_affected": {
            "MUNDKA": [
                "11KV FDR J.J COLONEY NO.\u2212"
            ]
        }
    },
    {
        "country": "India",
        "start": "2025-03-17_11-00-00",
        "end": "2025-03-17_14-00-00",
        "duration_(hours)": 3,
        "event_category": "maintenance schedule",
        "area_affected": {
            "JANAKPURI": [
                "11KV FDR PLOT NO-13 LIC BUILDING(DC"
            ]
        }
    },
    {
        "country": "India",
        "start": "2025-03-17_11-00-00",
        "end": "2025-03-17_14-00-00",
        "duration_(hours)": 3,
        "event_category": "maintenance schedule",
        "area_affected": {
            "VASANT KUNJ": [
                "11KV FDR VASANT KUNJ PKT-"
            ]
        }
    },
    {
        "country": "India",
        "start": "2025-03-17_11-00-00",
        "end": "2025-03-17_14-00-00",
        "duration_(hours)": 3,
        "event_category": "maintenance schedule",
        "area_affected": {
            "R K PURAM": [
                "11KV FDR O/G F-BLOCK VASANT VIHA"
            ]
        }
    },
    {
        "country": "India",
        "start": "2025-03-17_11-00-00",
        "end": "2025-03-17_14-00-00",
        "duration_(hours)": 3,
        "event_category": "maintenance schedule",
        "area_affected": {
            "NAJAFGARH": [
                "11KV FDR 7 PANEL BOAR"
            ]
        }
    },
    {
        "country": "India",
        "start": "2025-03-17_11-00-00",
        "end": "2025-03-17_14-00-00",
        "duration_(hours)": 3,
        "event_category": "maintenance schedule",
        "area_affected": {
            "SARITA VIHAR": [
                "11KV FDR O/G TORONTO SCHOOL MADANPUR KHADA"
            ]
        }
    },
    {
        "country": "India",
        "start": "2025-03-17_11-00-00",
        "end": "2025-03-17_14-00-00",
        "duration_(hours)": 3,
        "event_category": "maintenance schedule",
        "area_affected": {
            "JANAKPURI": [
                "11KV FDR RAIL MASTE"
            ]
        }
    },
    {
        "country": "India",
        "start": "2025-03-17_11-00-00",
        "end": "2025-03-17_14-00-00",
        "duration_(hours)": 3,
        "event_category": "maintenance schedule",
        "area_affected": {
            "VASANT KUNJ": [
                "11KV FDR O/G TO LIVER INSTITUTE VASANT KUN"
            ]
        }
    },
    {
        "country": "India",
        "start": "2025-03-17_11-00-00",
        "end": "2025-03-17_14-00-00",
        "duration_(hours)": 3,
        "event_category": "maintenance schedule",
        "area_affected": {
            "MOHAN GARDEN": [
                "11KV FDR PRATAP ENCLAV"
            ]
        }
    },
    {
        "country": "India",
        "start": "2025-03-17_11-00-00",
        "end": "2025-03-17_14-00-00",
        "duration_(hours)": 3,
        "event_category": "maintenance schedule",
        "area_affected": {
            "ALAKNANDA": [
                "11KV FDR O/G EPDP NO.-"
            ]
        }
    },
    {
        "country": "India",
        "start": "2025-03-17_11-00-00",
        "end": "2025-03-17_14-00-00",
        "duration_(hours)": 3,
        "event_category": "maintenance schedule",
        "area_affected": {
            "PALAM": [
                "11KV FDR DABRI NO "
            ]
        }
    },
    {
        "country": "India",
        "start": "2025-03-17_11-00-00",
        "end": "2025-03-17_14-00-00",
        "duration_(hours)": 3,
        "event_category": "maintenance schedule",
        "area_affected": {
            "NANGLOI": [
                "11KV FDR P.V.C. MKT.JAWALA PURI ( R\u2212BLOCK "
            ]
        }
    },
    {
        "country": "India",
        "start": "2025-03-17_11-00-00",
        "end": "2025-03-17_14-00-00",
        "duration_(hours)": 3,
        "event_category": "maintenance schedule",
        "area_affected": {
            "R K PURAM": [
                "11KV FDR O/G R.K PURAM WEST BLOC"
            ]
        }
    },
    {
        "country": "India",
        "start": "2025-03-17_11-00-00",
        "end": "2025-03-17_14-00-00",
        "duration_(hours)": 3,
        "event_category": "maintenance schedule",
        "area_affected": {
            "NIZAMUDDIN": [
                "11KV FDR O/G B\u2212BLOCK DEFENCE COLON"
            ]
        }
    },
    {
        "country": "India",
        "start": "2025-03-17_11-00-00",
        "end": "2025-03-17_14-00-00",
        "duration_(hours)": 3,
        "event_category": "maintenance schedule",
        "area_affected": {
            "NEW FRIENDS COLONY": [
                "11KV FDR A.F.E. M-BLOC"
            ]
        }
    },
    {
        "country": "India",
        "start": "2025-03-17_11-00-00",
        "end": "2025-03-17_14-00-00",
        "duration_(hours)": 3,
        "event_category": "maintenance schedule",
        "area_affected": {
            "HAUZ KHAS": [
                "11KV FDR 11KV O/G TO S-BLOCK PANCHSHEEL PAR"
            ]
        }
    },
    {
        "country": "India",
        "start": "2025-03-17_11-00-00",
        "end": "2025-03-17_14-00-00",
        "duration_(hours)": 3,
        "event_category": "maintenance schedule",
        "area_affected": {
            "NAJAFGARH": [
                "11KV FDR BABA HARIDA"
            ]
        }
    },
    {
        "country": "India",
        "start": "2025-03-17_11-00-00",
        "end": "2025-03-17_14-00-00",
        "duration_(hours)": 3,
        "event_category": "maintenance schedule",
        "area_affected": {
            "VIKASPURI": [
                "11KV FDR SHIV VIHA"
            ]
        }
    },
    {
        "country": "India",
        "start": "2025-03-17_11-00-00",
        "end": "2025-03-17_14-00-00",
        "duration_(hours)": 3,
        "event_category": "maintenance schedule",
        "area_affected": {
            "SAKET": [
                "11KV FDR O/G TO 80\u2212BLOCK MALVIYA NAGA"
            ]
        }
    },
    {
        "country": "India",
        "start": "2025-03-17_11-00-00",
        "end": "2025-03-17_14-00-00",
        "duration_(hours)": 3,
        "event_category": "maintenance schedule",
        "area_affected": {
            "JANAKPURI": [
                "11KV FDR RAWT"
            ]
        }
    },
    {
        "country": "India",
        "start": "2025-03-17_11-00-00",
        "end": "2025-03-17_14-00-00",
        "duration_(hours)": 3,
        "event_category": "maintenance schedule",
        "area_affected": {
            "TAGORE GARDEN": [
                "11KV FDR F-BLOCK SHIVAJI ENCLAV"
            ]
        }
    },
    {
        "country": "India",
        "start": "2025-03-17_11-00-00",
        "end": "2025-03-17_14-00-00",
        "duration_(hours)": 3,
        "event_category": "maintenance schedule",
        "area_affected": {
            "NIZAMUDDIN": [
                "11KV FDR LAJPAT NAGAR 1",
                " FEEDER NO.\u2212"
            ]
        }
    },
    {
        "country": "India",
        "start": "2025-03-17_11-00-00",
        "end": "2025-03-17_14-00-00",
        "duration_(hours)": 3,
        "event_category": "maintenance schedule",
        "area_affected": {
            "KHANPUR": [
                "11KV FDR O/G TO TIN WALA S/STN. C-BLOCK SANGAM VHR"
            ]
        }
    },
    {
        "country": "India",
        "start": "2025-03-17_11-00-00",
        "end": "2025-03-17_14-00-00",
        "duration_(hours)": 3,
        "event_category": "maintenance schedule",
        "area_affected": {
            "NAJAFGARH": [
                "11KV FDR DICHOA"
            ]
        }
    },
    {
        "country": "India",
        "start": "2025-03-17_11-00-00",
        "end": "2025-03-17_14-00-00",
        "duration_(hours)": 3,
        "event_category": "maintenance schedule",
        "area_affected": {
            "KHANPUR": [
                "11KV FDR O/G S/S NO.5 DAKSHINPUR"
            ]
        }
    },
    {
        "country": "India",
        "start": "2025-03-17_11-00-00",
        "end": "2025-03-17_14-00-00",
        "duration_(hours)": 3,
        "event_category": "maintenance schedule",
        "area_affected": {
            "UTTAM NAGAR": [
                "11KV FDR PREM NAGA"
            ]
        }
    },
    {
        "country": "India",
        "start": "2025-03-17_11-00-00",
        "end": "2025-03-17_14-00-00",
        "duration_(hours)": 3,
        "event_category": "maintenance schedule",
        "area_affected": {
            "ALAKNANDA": [
                "11KV FDR SSTN NO.2 SLUM FLATS",
                " A\u221214",
                " KALKA JI",
                " EXT"
            ]
        }
    },
    {
        "country": "India",
        "start": "2025-03-17_11-00-00",
        "end": "2025-03-17_14-00-00",
        "duration_(hours)": 3,
        "event_category": "maintenance schedule",
        "area_affected": {
            "CHHATARPUR": [
                "11KV FDR O/G TO MANGALAPUR"
            ]
        }
    },
    {
        "country": "India",
        "start": "2025-03-17_11-00-00",
        "end": "2025-03-17_14-00-00",
        "duration_(hours)": 3,
        "event_category": "maintenance schedule",
        "area_affected": {
            "NAJAFGARH": [
                "11KV FDR PUMPING STATIO"
            ]
        }
    },
    {
        "country": "India",
        "start": "2025-03-17_11-00-00",
        "end": "2025-03-17_14-00-00",
        "duration_(hours)": 3,
        "event_category": "maintenance schedule",
        "area_affected": {
            "UTTAM NAGAR": [
                "11KV FDR J.J COLONY MACHHI MK"
            ]
        }
    },
    {
        "country": "India",
        "start": "2025-03-17_11-00-00",
        "end": "2025-03-17_14-00-00",
        "duration_(hours)": 3,
        "event_category": "maintenance schedule",
        "area_affected": {
            "SARITA VIHAR": [
                "11KV FDR SOURABH VIHAR-"
            ]
        }
    },
    {
        "country": "India",
        "start": "2025-03-17_11-00-00",
        "end": "2025-03-17_14-00-00",
        "duration_(hours)": 3,
        "event_category": "maintenance schedule",
        "area_affected": {
            "CHHATARPUR": [
                "11KV FDR DLF GATE NO.-2 (MAIDAN GARHI"
            ]
        }
    },
    {
        "country": "India",
        "start": "2025-03-17_11-00-00",
        "end": "2025-03-17_14-00-00",
        "duration_(hours)": 3,
        "event_category": "maintenance schedule",
        "area_affected": {
            "MUNDKA": [
                "11KV FDR JAI VIHA"
            ]
        }
    },
    {
        "country": "India",
        "start": "2025-03-17_11-00-00",
        "end": "2025-03-17_14-00-00",
        "duration_(hours)": 3,
        "event_category": "maintenance schedule",
        "area_affected": {
            "MOHAN GARDEN": [
                "11KV FDR A-BLOCK MANDIRWAL"
            ]
        }
    },
    {
        "country": "India",
        "start": "2025-03-17_11-00-00",
        "end": "2025-03-17_14-00-00",
        "duration_(hours)": 3,
        "event_category": "maintenance schedule",
        "area_affected": {
            "JANAKPURI": [
                "11KV FDR SURAKHPUR ROAD GOPAL NAGA"
            ]
        }
    },
    {
        "country": "India",
        "start": "2025-03-17_11-00-00",
        "end": "2025-03-17_14-00-00",
        "duration_(hours)": 3,
        "event_category": "maintenance schedule",
        "area_affected": {
            "MUNDKA": [
                "11KV FDR KAMRUDEEN NGR"
            ]
        }
    },
    {
        "country": "India",
        "start": "2025-03-17_11-00-00",
        "end": "2025-03-17_14-00-00",
        "duration_(hours)": 3,
        "event_category": "maintenance schedule",
        "area_affected": {
            "JANAKPURI": [
                "11KV FDR DHANS"
            ]
        }
    },
    {
        "country": "India",
        "start": "2025-03-17_11-00-00",
        "end": "2025-03-17_14-00-00",
        "duration_(hours)": 3,
        "event_category": "maintenance schedule",
        "area_affected": {
            "UTTAM NAGAR": [
                "11KV FDR R & S BLOCK CHANAKYA PLAC"
            ]
        }
    },
    {
        "country": "India",
        "start": "2025-03-17_11-00-00",
        "end": "2025-03-17_14-00-00",
        "duration_(hours)": 3,
        "event_category": "maintenance schedule",
        "area_affected": {
            "NAJAFGARH": [
                "11KV MCD SCHOOL QUTUB VIHA"
            ]
        }
    },
    {
        "country": "India",
        "start": "2025-03-17_11-00-00",
        "end": "2025-03-17_15-00-00",
        "duration_(hours)": 4,
        "event_category": "maintenance schedule",
        "area_affected": {
            "NANGLOI": [
                "11KV FDR NILOTH"
            ]
        }
    },
    {
        "country": "India",
        "start": "2025-03-17_11-00-00",
        "end": "2025-03-17_14-00-00",
        "duration_(hours)": 3,
        "event_category": "maintenance schedule",
        "area_affected": {
            "TAGORE GARDEN": [
                "11KV FDR 608 JANTA FLA"
            ]
        }
    },
    {
        "country": "India",
        "start": "2025-03-17_11-00-00",
        "end": "2025-03-17_14-00-00",
        "duration_(hours)": 3,
        "event_category": "maintenance schedule",
        "area_affected": {
            "MUNDKA": [
                "11KV FDR SUBASH VIHAR-"
            ]
        }
    },
    {
        "country": "India",
        "start": "2025-03-17_11-00-00",
        "end": "2025-03-17_12-00-00",
        "duration_(hours)": 1,
        "event_category": "maintenance schedule",
        "area_affected": {
            "VIKASPURI": [
                "11KV FDR RAJHANS VIHA"
            ]
        }
    },
    {
        "country": "India",
        "start": "2025-03-17_11-00-00",
        "end": "2025-03-17_14-00-00",
        "duration_(hours)": 3,
        "event_category": "maintenance schedule",
        "area_affected": {
            "NANGLOI": [
                "11KV FDR A BLK NIHAL VIHAR+11KV FDR RADISSON HOTE"
            ]
        }
    },
    {
        "country": "India",
        "start": "2025-03-17_11-00-00",
        "end": "2025-03-17_14-00-00",
        "duration_(hours)": 3,
        "event_category": "maintenance schedule",
        "area_affected": {
            "UTTAM NAGAR": [
                "11KV FDR UTTAM NAGA"
            ]
        }
    },
    {
        "country": "India",
        "start": "2025-03-17_11-00-00",
        "end": "2025-03-17_14-00-00",
        "duration_(hours)": 3,
        "event_category": "maintenance schedule",
        "area_affected": {
            "JANAKPURI": [
                "11KV FDR A-4 JKP( ASALAT PUR"
            ]
        }
    },
    {
        "country": "India",
        "start": "2025-03-17_10-00-00",
        "end": "2025-03-17_13-00-00",
        "duration_(hours)": 3,
        "event_category": "maintenance schedule",
        "area_affected": {
            "VASANT KUNJ": [
                "11KV FDR B-8 V. KUNJ (VIA GOINKA SCHOOL"
            ]
        }
    },
    {
        "country": "India",
        "start": "2025-03-17_10-00-00",
        "end": "2025-03-17_13-00-00",
        "duration_(hours)": 3,
        "event_category": "maintenance schedule",
        "area_affected": {
            "SAKET": [
                "11KV FDR OG TO J-12 SAKE"
            ]
        }
    },
    {
        "country": "India",
        "start": "2025-03-17_10-00-00",
        "end": "2025-03-17_13-00-00",
        "duration_(hours)": 3,
        "event_category": "maintenance schedule",
        "area_affected": {
            "PUNJABI BAGH": [
                "11KV FDR BOOSTER PUMP PUNJABI BAG"
            ]
        }
    },
    {
        "country": "India",
        "start": "2025-03-17_10-00-00",
        "end": "2025-03-17_13-00-00",
        "duration_(hours)": 3,
        "event_category": "maintenance schedule",
        "area_affected": {
            "NAJAFGARH": [
                "11KV FDR RAMA PAR"
            ]
        }
    },
    {
        "country": "India",
        "start": "2025-03-17_10-00-00",
        "end": "2025-03-17_13-00-00",
        "duration_(hours)": 3,
        "event_category": "maintenance schedule",
        "area_affected": {
            "VASANT KUNJ": [
                "11KV FDR O/G TO CENTAUR HOTE"
            ]
        }
    },
    {
        "country": "India",
        "start": "2025-03-17_10-00-00",
        "end": "2025-03-17_13-00-00",
        "duration_(hours)": 3,
        "event_category": "maintenance schedule",
        "area_affected": {
            "JANAKPURI": [
                "11KV FDR MOHAN NAGAR MANDIR WAL"
            ]
        }
    },
    {
        "country": "India",
        "start": "2025-03-17_10-00-00",
        "end": "2025-03-17_13-00-00",
        "duration_(hours)": 3,
        "event_category": "maintenance schedule",
        "area_affected": {
            "UTTAM NAGAR": [
                "11KV FDR KIRAN GARDEN PM NEAR MAHINDRU PAR"
            ]
        }
    },
    {
        "country": "India",
        "start": "2025-03-17_10-00-00",
        "end": "2025-03-17_13-00-00",
        "duration_(hours)": 3,
        "event_category": "maintenance schedule",
        "area_affected": {
            "DWARKA": [
                "11KV FDR GGSIP UNIVERSIT"
            ]
        }
    },
    {
        "country": "India",
        "start": "2025-03-17_10-00-00",
        "end": "2025-03-17_13-00-00",
        "duration_(hours)": 3,
        "event_category": "maintenance schedule",
        "area_affected": {
            "TAGORE GARDEN": [
                "11KV FDR TILAK VIHA"
            ]
        }
    },
    {
        "country": "India",
        "start": "2025-03-17_10-00-00",
        "end": "2025-03-17_13-00-00",
        "duration_(hours)": 3,
        "event_category": "maintenance schedule",
        "area_affected": {
            "VASANT KUNJ": [
                "11KV FDR O/G RAJOKAR"
            ]
        }
    },
    {
        "country": "India",
        "start": "2025-03-17_10-00-00",
        "end": "2025-03-17_13-00-00",
        "duration_(hours)": 3,
        "event_category": "maintenance schedule",
        "area_affected": {
            "DWARKA": [
                "11KV FDR OPG SCHOOL SEC-19-"
            ]
        }
    },
    {
        "country": "India",
        "start": "2025-03-17_10-00-00",
        "end": "2025-03-17_13-00-00",
        "duration_(hours)": 3,
        "event_category": "maintenance schedule",
        "area_affected": {
            "VASANT KUNJ": [
                "11KV FDR O/G TO RANGPURI NO.-"
            ]
        }
    },
    {
        "country": "India",
        "start": "2025-03-17_10-00-00",
        "end": "2025-03-17_14-00-00",
        "duration_(hours)": 4,
        "event_category": "maintenance schedule",
        "area_affected": {
            "SAKET": [
                "11KV FDR S/S NO.-11",
                " SEC-4 PUSHP VIHA"
            ]
        }
    },
    {
        "country": "India",
        "start": "2025-03-17_10-00-00",
        "end": "2025-03-17_13-00-00",
        "duration_(hours)": 3,
        "event_category": "maintenance schedule",
        "area_affected": {
            "NANGLOI": [
                "11KV FDR SHANKAR GARDE"
            ]
        }
    },
    {
        "country": "India",
        "start": "2025-03-17_10-00-00",
        "end": "2025-03-17_13-00-00",
        "duration_(hours)": 3,
        "event_category": "maintenance schedule",
        "area_affected": {
            "DWARKA": [
                "11KV FDR S/STN\u22125 1568 DDA FLATS SEC\u221214",
                " DWK + 11KV FDR MUTHOOT HOSPITAL SEC-10 NO-"
            ]
        }
    },
    {
        "country": "India",
        "start": "2025-03-17_10-00-00",
        "end": "2025-03-17_13-00-00",
        "duration_(hours)": 3,
        "event_category": "maintenance schedule",
        "area_affected": {
            "NAJAFGARH": [
                "11KV FDR DJB-"
            ]
        }
    },
    {
        "country": "India",
        "start": "2025-03-17_10-00-00",
        "end": "2025-03-17_13-00-00",
        "duration_(hours)": 3,
        "event_category": "maintenance schedule",
        "area_affected": {
            "NAJAFGARH": [
                "11KV FDR SOMESH VIHA"
            ]
        }
    },
    {
        "country": "India",
        "start": "2025-03-17_10-00-00",
        "end": "2025-03-17_13-00-00",
        "duration_(hours)": 3,
        "event_category": "maintenance schedule",
        "area_affected": {
            "VIKASPURI": [
                "11KV FDR LOK VIHAR VK"
            ]
        }
    },
    {
        "country": "India",
        "start": "2025-03-17_10-00-00",
        "end": "2025-03-17_13-00-00",
        "duration_(hours)": 3,
        "event_category": "maintenance schedule",
        "area_affected": {
            "SAKET": [
                "11KV FDR SARVODAYA ENCLAV"
            ]
        }
    },
    {
        "country": "India",
        "start": "2025-03-17_10-00-00",
        "end": "2025-03-17_13-00-00",
        "duration_(hours)": 3,
        "event_category": "maintenance schedule",
        "area_affected": {
            "MOHAN GARDEN": [
                "11KV FDR C BLOCK SEWAK PARK+11KV FDR NAWAD SCHOOLWAL"
            ]
        }
    },
    {
        "country": "India",
        "start": "2025-03-17_10-00-00",
        "end": "2025-03-17_13-00-00",
        "duration_(hours)": 3,
        "event_category": "maintenance schedule",
        "area_affected": {
            "PUNJABI BAGH": [
                "11KV FDR MULTAN NAGAR (C-BLOCK"
            ]
        }
    },
    {
        "country": "India",
        "start": "2025-03-17_10-00-00",
        "end": "2025-03-17_13-00-00",
        "duration_(hours)": 3,
        "event_category": "maintenance schedule",
        "area_affected": {
            "PUNJABI BAGH": [
                "11KV FDR B-G-3 PRAGATI APPT. PASCHIM VIHA"
            ]
        }
    },
    {
        "country": "India",
        "start": "2025-03-17_10-00-00",
        "end": "2025-03-17_13-00-00",
        "duration_(hours)": 3,
        "event_category": "maintenance schedule",
        "area_affected": {
            "KHANPUR": [
                "11KV FDR O/G F-2 PLINTH MOUNTED SANGAM VIHA"
            ]
        }
    },
    {
        "country": "India",
        "start": "2025-03-17_10-00-00",
        "end": "2025-03-17_13-00-00",
        "duration_(hours)": 3,
        "event_category": "maintenance schedule",
        "area_affected": {
            "DWARKA": [
                "11KV FDR SHIV PARK KAKROL"
            ]
        }
    },
    {
        "country": "India",
        "start": "2025-03-17_10-00-00",
        "end": "2025-03-17_13-00-00",
        "duration_(hours)": 3,
        "event_category": "maintenance schedule",
        "area_affected": {
            "NAJAFGARH": [
                "11KV FDR PAPRAWA"
            ]
        }
    },
    {
        "country": "India",
        "start": "2025-03-17_10-00-00",
        "end": "2025-03-17_13-00-00",
        "duration_(hours)": 3,
        "event_category": "maintenance schedule",
        "area_affected": {
            "NEHRU PLACE": [
                "11KV FDR O/G 39 RING ROA"
            ]
        }
    },
    {
        "country": "India",
        "start": "2025-03-17_10-00-00",
        "end": "2025-03-17_13-00-00",
        "duration_(hours)": 3,
        "event_category": "maintenance schedule",
        "area_affected": {
            "JANAKPURI": [
                "11KV FDR GURUDWARA R GARDE"
            ]
        }
    },
    {
        "country": "India",
        "start": "2025-03-17_10-00-00",
        "end": "2025-03-17_13-00-00",
        "duration_(hours)": 3,
        "event_category": "maintenance schedule",
        "area_affected": {
            "JANAKPURI": [
                "11KV FDR NANGLI ZALI"
            ]
        }
    },
    {
        "country": "India",
        "start": "2025-03-17_10-00-00",
        "end": "2025-03-17_14-00-00",
        "duration_(hours)": 4,
        "event_category": "maintenance schedule",
        "area_affected": {
            "JANAKPURI": [
                "11KV FDR GHUMANHERA MOR"
            ]
        }
    },
    {
        "country": "India",
        "start": "2025-03-17_10-00-00",
        "end": "2025-03-17_13-00-00",
        "duration_(hours)": 3,
        "event_category": "maintenance schedule",
        "area_affected": {
            "DWARKA": [
                "11KV FDR S/STN NO-4 L & T FLATS SEC-1"
            ]
        }
    },
    {
        "country": "India",
        "start": "2025-03-17_10-00-00",
        "end": "2025-03-17_13-00-00",
        "duration_(hours)": 3,
        "event_category": "maintenance schedule",
        "area_affected": {
            "JANAKPURI": [
                "11KV FDR DABAR ENCLAV"
            ]
        }
    },
    {
        "country": "India",
        "start": "2025-03-17_10-00-00",
        "end": "2025-03-17_13-00-00",
        "duration_(hours)": 3,
        "event_category": "maintenance schedule",
        "area_affected": {
            "NAJAFGARH": [
                "11KV FDR KHARKHERI NAHA"
            ]
        }
    },
    {
        "country": "India",
        "start": "2025-03-17_10-00-00",
        "end": "2025-03-17_14-00-00",
        "duration_(hours)": 4,
        "event_category": "maintenance schedule",
        "area_affected": {
            "JANAKPURI": [
                "11KV FDR NEW MUNDHEL"
            ]
        }
    },
    {
        "country": "India",
        "start": "2025-03-17_10-00-00",
        "end": "2025-03-17_13-00-00",
        "duration_(hours)": 3,
        "event_category": "maintenance schedule",
        "area_affected": {
            "KHANPUR": [
                "11KV FDR O/G HOT MIX PLAN"
            ]
        }
    },
    {
        "country": "India",
        "start": "2025-03-17_10-00-00",
        "end": "2025-03-17_14-00-00",
        "duration_(hours)": 4,
        "event_category": "maintenance schedule",
        "area_affected": {
            "JANAKPURI": [
                "11KV FDR SHYAM ENCLAV"
            ]
        }
    },
    {
        "country": "India",
        "start": "2025-03-17_10-00-00",
        "end": "2025-03-17_13-00-00",
        "duration_(hours)": 3,
        "event_category": "maintenance schedule",
        "area_affected": {
            "NAJAFGARH": [
                "11KV FDR TP KOTL"
            ]
        }
    },
    {
        "country": "India",
        "start": "2025-03-17_10-00-00",
        "end": "2025-03-17_13-00-00",
        "duration_(hours)": 3,
        "event_category": "maintenance schedule",
        "area_affected": {
            "KHANPUR": [
                "11KV FDR OG TO D-BLOCK SANGAM VIHAR (OLD"
            ]
        }
    },
    {
        "country": "India",
        "start": "2025-03-17_10-00-00",
        "end": "2025-03-17_14-00-00",
        "duration_(hours)": 4,
        "event_category": "maintenance schedule",
        "area_affected": {
            "JANAKPURI": [
                "11KV FDR MALIK PU"
            ]
        }
    },
    {
        "country": "India",
        "start": "2025-03-17_10-00-00",
        "end": "2025-03-17_14-00-00",
        "duration_(hours)": 4,
        "event_category": "maintenance schedule",
        "area_affected": {
            "JANAKPURI": [
                "11KV FDR P-BLOCK GOPAL NAGAR FEEDE"
            ]
        }
    },
    {
        "country": "India",
        "start": "2025-03-17_11-00-00",
        "end": "2025-03-17_14-00-00",
        "duration_(hours)": 3,
        "event_category": "maintenance schedule",
        "area_affected": {
            "UTTAM NAGAR": [
                "BLOCK A 3 HARJAN COLONY SITAPURI PART 1 SITAPURI"
            ]
        }
    },
    {
        "country": "India",
        "start": "2025-03-17_11-00-00",
        "end": "2025-03-17_14-00-00",
        "duration_(hours)": 3,
        "event_category": "maintenance schedule",
        "area_affected": {
            "R K PURAM": [
                "SECR 7 RAMAKRISHNA PURAM"
            ]
        }
    },
    {
        "country": "India",
        "start": "2025-03-17_11-00-00",
        "end": "2025-03-17_14-00-00",
        "duration_(hours)": 3,
        "event_category": "maintenance schedule",
        "area_affected": {
            "SARITA VIHAR": [
                "MOHAN BABA NAGAR TAJPUR PAHARI VILLAGE BADARPUR",
                "BADARPUR EXTENSION TAJPUR BADARPUR"
            ]
        }
    },
    {
        "country": "India",
        "start": "2025-03-17_11-00-00",
        "end": "2025-03-17_14-00-00",
        "duration_(hours)": 3,
        "event_category": "maintenance schedule",
        "area_affected": {
            "R K PURAM": [
                "INDIAN AIR LINES AND AIR INDIA ESTATE VASANT VIHAR"
            ]
        }
    },
    {
        "country": "India",
        "start": "2025-03-17_11-00-00",
        "end": "2025-03-17_14-00-00",
        "duration_(hours)": 3,
        "event_category": "maintenance schedule",
        "area_affected": {
            "NIZAMUDDIN": [
                "BLOCK H LAJPAT NAGAR III LAJPAT NAGAR"
            ]
        }
    },
    {
        "country": "India",
        "start": "2025-03-17_11-00-00",
        "end": "2025-03-17_14-00-00",
        "duration_(hours)": 3,
        "event_category": "maintenance schedule",
        "area_affected": {
            "CHHATARPUR": [
                "MANGLAPURI VILLAGE SULTANPUR"
            ]
        }
    },
    {
        "country": "India",
        "start": "2025-03-17_11-00-00",
        "end": "2025-03-17_14-00-00",
        "duration_(hours)": 3,
        "event_category": "maintenance schedule",
        "area_affected": {
            "VIKASPURI": [
                "SHIV VIHAR HASTSAL",
                "SHIV VIHAR WEST",
                "S-BLOCK VIKAS NAGAR",
                "GUPTA ENCLAVE",
                "SHIV VIHAR COLONY",
                "R&S BLOCK VIKAS NAGAR",
                "F-BLOCK VIKAS NAGAR",
                "D-BLOCK JJ COLONY"
            ]
        }
    },
    {
        "country": "India",
        "start": "2025-03-17_11-00-00",
        "end": "2025-03-17_14-00-00",
        "duration_(hours)": 3,
        "event_category": "maintenance schedule",
        "area_affected": {
            "MUNDKA": [
                "TIKRI KALAN"
            ]
        }
    },
    {
        "country": "India",
        "start": "2025-03-17_11-00-00",
        "end": "2025-03-17_14-00-00",
        "duration_(hours)": 3,
        "event_category": "maintenance schedule",
        "area_affected": {
            "JAFFARPUR": [
                "ISSAPUR VILLAGE",
                "BAQAR GARH VILLAGE",
                "BADHOSRA",
                "JAFARPUR KALAN VILLAGE",
                "QAZIPUR VILLAGE",
                "MANDHELA KALAN VILLAGE"
            ]
        }
    },
    {
        "country": "India",
        "start": "2025-03-17_11-00-00",
        "end": "2025-03-17_14-00-00",
        "duration_(hours)": 3,
        "event_category": "maintenance schedule",
        "area_affected": {
            "VASANT KUNJ": [
                "GHIRNI VILLAGE GHIRNI"
            ]
        }
    },
    {
        "country": "India",
        "start": "2025-03-17_11-00-00",
        "end": "2025-03-17_14-00-00",
        "duration_(hours)": 3,
        "event_category": "maintenance schedule",
        "area_affected": {
            "NAJAFGARH": [
                "JHARODA KALAN"
            ]
        }
    },
    {
        "country": "India",
        "start": "2025-03-17_11-00-00",
        "end": "2025-03-17_14-00-00",
        "duration_(hours)": 3,
        "event_category": "maintenance schedule",
        "area_affected": {
            "TAGORE GARDEN": [
                "BLOCK D TAGORE GARDEN TAGORE GARDEN EXTENSION"
            ]
        }
    },
    {
        "country": "India",
        "start": "2025-03-17_11-00-00",
        "end": "2025-03-17_14-00-00",
        "duration_(hours)": 3,
        "event_category": "maintenance schedule",
        "area_affected": {
            "TAGORE GARDEN": [
                "RAVI NAGAR VISHNU GARDEN"
            ]
        }
    },
    {
        "country": "India",
        "start": "2025-03-17_11-00-00",
        "end": "2025-03-17_14-00-00",
        "duration_(hours)": 3,
        "event_category": "maintenance schedule",
        "area_affected": {
            "NEW FRIENDS COLONY": [
                "BLOCK G PART 1 ABUL FAZAL ENCLAVE JAMIA NAGAR OKHLA"
            ]
        }
    },
    {
        "country": "India",
        "start": "2025-03-17_11-00-00",
        "end": "2025-03-17_14-00-00",
        "duration_(hours)": 3,
        "event_category": "maintenance schedule",
        "area_affected": {
            "MOHAN GARDEN": [
                "BLOCK N 2 MOHAN GARDEN RAZAPUR KHURD"
            ]
        }
    },
    {
        "country": "India",
        "start": "2025-03-17_11-00-00",
        "end": "2025-03-17_14-00-00",
        "duration_(hours)": 3,
        "event_category": "maintenance schedule",
        "area_affected": {
            "NEHRU PLACE": [
                "BLOCK G KAILASH COLONY GREATER KAILASH"
            ]
        }
    },
    {
        "country": "India",
        "start": "2025-03-17_11-00-00",
        "end": "2025-03-17_14-00-00",
        "duration_(hours)": 3,
        "event_category": "maintenance schedule",
        "area_affected": {
            "HAUZ KHAS": [
                "BLOCK C PANCHSHEEL ENCLAVE"
            ]
        }
    },
    {
        "country": "India",
        "start": "2025-03-17_11-00-00",
        "end": "2025-03-17_14-00-00",
        "duration_(hours)": 3,
        "event_category": "maintenance schedule",
        "area_affected": {
            "JAFFARPUR": [
                "MANDHELA KHURD VILLAGE",
                "MANDHELA KALAN VILLAGE",
                "RAWTA JAFARPUR KALAN VILLAGE",
                "KAIR VILLAGE"
            ]
        }
    },
    {
        "country": "India",
        "start": "2025-03-17_11-00-00",
        "end": "2025-03-17_14-00-00",
        "duration_(hours)": 3,
        "event_category": "maintenance schedule",
        "area_affected": {
            "JAFFARPUR": [
                "MITRAON VILLAGE NAJAFGARH",
                "SUREHRA VILLAGE"
            ]
        }
    },
    {
        "country": "India",
        "start": "2025-03-17_11-00-00",
        "end": "2025-03-17_14-00-00",
        "duration_(hours)": 3,
        "event_category": "maintenance schedule",
        "area_affected": {
            "VASANT KUNJ": [
                "KISHANGARH VILLAGE SECR A VASANT KUNJ"
            ]
        }
    },
    {
        "country": "India",
        "start": "2025-03-17_11-00-00",
        "end": "2025-03-17_14-00-00",
        "duration_(hours)": 3,
        "event_category": "maintenance schedule",
        "area_affected": {
            "MOHAN GARDEN": [
                "BLOCK M ZAILDAR ENCLAVE HASTSAL",
                "BLOCK F ZAILDAR ENCLAVE NAWADA"
            ]
        }
    },
    {
        "country": "India",
        "start": "2025-03-17_11-00-00",
        "end": "2025-03-17_14-00-00",
        "duration_(hours)": 3,
        "event_category": "maintenance schedule",
        "area_affected": {
            "NIZAMUDDIN": [
                "BLOCK N SOUTH EXTENSION PART 1"
            ]
        }
    },
    {
        "country": "India",
        "start": "2025-03-17_11-00-00",
        "end": "2025-03-17_14-00-00",
        "duration_(hours)": 3,
        "event_category": "maintenance schedule",
        "area_affected": {
            "VIKASPURI": [
                "SHIV VIHAR HASTSAL",
                "SHIV VIHAR WEST",
                "S-BLOCK VIKAS NAGAR",
                "GUPTA ENCLAVE",
                "SHIV VIHAR COLONY",
                "R&S BLOCK VIKAS NAGAR",
                "F-BLOCK VIKAS NAGAR",
                "D-BLOCK JJ COLONY"
            ]
        }
    },
    {
        "country": "India",
        "start": "2025-03-17_11-00-00",
        "end": "2025-03-17_14-00-00",
        "duration_(hours)": 3,
        "event_category": "maintenance schedule",
        "area_affected": {
            "JAFFARPUR": [
                "RAWTA JAFARPUR KALAN VILLAGE",
                "JAFARPUR KALAN VILLAGE"
            ]
        }
    },
    {
        "country": "India",
        "start": "2025-03-17_11-00-00",
        "end": "2025-03-17_14-00-00",
        "duration_(hours)": 3,
        "event_category": "maintenance schedule",
        "area_affected": {
            "SARITA VIHAR": [
                "RAJ NAGAR MADANPUR KHADAR"
            ]
        }
    },
    {
        "country": "India",
        "start": "2025-03-17_11-00-00",
        "end": "2025-03-17_14-00-00",
        "duration_(hours)": 3,
        "event_category": "maintenance schedule",
        "area_affected": {
            "SARITA VIHAR": [
                "POCKET E SARITA VIHAR"
            ]
        }
    },
    {
        "country": "India",
        "start": "2025-03-17_11-00-00",
        "end": "2025-03-17_14-00-00",
        "duration_(hours)": 3,
        "event_category": "maintenance schedule",
        "area_affected": {
            "ALAKNANDA": [
                "A14-BLOCK KALKA JI EXTN_DDA FLATS KALKAJI"
            ]
        }
    },
    {
        "country": "India",
        "start": "2025-03-17_11-00-00",
        "end": "2025-03-17_14-00-00",
        "duration_(hours)": 3,
        "event_category": "maintenance schedule",
        "area_affected": {
            "NIZAMUDDIN": [
                "BLOCK N SOUTH EXTENSION PART 1"
            ]
        }
    },
    {
        "country": "India",
        "start": "2025-03-17_11-00-00",
        "end": "2025-03-17_14-00-00",
        "duration_(hours)": 3,
        "event_category": "maintenance schedule",
        "area_affected": {
            "ALAKNANDA": [
                "H-BLOCK CR PARK"
            ]
        }
    },
    {
        "country": "India",
        "start": "2025-03-17_11-00-00",
        "end": "2025-03-17_14-00-00",
        "duration_(hours)": 3,
        "event_category": "maintenance schedule",
        "area_affected": {
            "MUNDKA": [
                "GULSHAN PARK WEST CABIN BLOCK MUNDKA"
            ]
        }
    },
    {
        "country": "India",
        "start": "2025-03-17_11-00-00",
        "end": "2025-03-17_14-00-00",
        "duration_(hours)": 3,
        "event_category": "maintenance schedule",
        "area_affected": {
            "HAUZ KHAS": [
                "HUMAYUNPUR SAFDARJUNG ENCLAVE"
            ]
        }
    },
    {
        "country": "India",
        "start": "2025-03-17_11-00-00",
        "end": "2025-03-17_14-00-00",
        "duration_(hours)": 3,
        "event_category": "maintenance schedule",
        "area_affected": {
            "CHHATARPUR": [
                "BLOCK C CHHATARPUR EXTENSION CHHATARPUR",
                "RAJPUR KHURD VILLAGE CHHATARPUR"
            ]
        }
    },
    {
        "country": "India",
        "start": "2025-03-17_11-00-00",
        "end": "2025-03-17_14-00-00",
        "duration_(hours)": 3,
        "event_category": "maintenance schedule",
        "area_affected": {
            "JAFFARPUR": [
                "RAWTA VILLAGE",
                "DAURALA VILLAGE",
                "GHALLBPUR VILLAGE",
                "DARYAPUR KHURD VILLAGE",
                "GHUMAN HERA JAINPUR VILLAGE",
                "GHUMANHERA"
            ]
        }
    },
    {
        "country": "India",
        "start": "2025-03-17_11-00-00",
        "end": "2025-03-17_14-00-00",
        "duration_(hours)": 3,
        "event_category": "maintenance schedule",
        "area_affected": {
            "JAFFARPUR": [
                "QAZIPUR VILLAGE",
                "SARANGPUR VILLAGE",
                "DHANSA VILLAGE",
                "JAFARPUR KALAN VILLAGE",
                "ISSAPUR VILLAGE",
                "SAMAZPUR KHALSA",
                "BADHOSRA"
            ]
        }
    },
    {
        "country": "India",
        "start": "2025-03-17_11-00-00",
        "end": "2025-03-17_14-00-00",
        "duration_(hours)": 3,
        "event_category": "maintenance schedule",
        "area_affected": {
            "NEW FRIENDS COLONY": [
                "BLOCK A NEW FRIENDS COLONY WEST NEW FRIENDS COLONY"
            ]
        }
    },
    {
        "country": "India",
        "start": "2025-03-17_11-00-00",
        "end": "2025-03-17_14-00-00",
        "duration_(hours)": 3,
        "event_category": "maintenance schedule",
        "area_affected": {
            "VASANT KUNJ": [
                "SHAHABAD MUHAMMADPUR VILLAGE DWARKA"
            ]
        }
    },
    {
        "country": "India",
        "start": "2025-03-17_11-00-00",
        "end": "2025-03-17_14-00-00",
        "duration_(hours)": 3,
        "event_category": "maintenance schedule",
        "area_affected": {
            "UTTAM NAGAR": [
                "BHAGWATI VIHAR BINDAPUR"
            ]
        }
    },
    {
        "country": "India",
        "start": "2025-03-17_11-00-00",
        "end": "2025-03-17_14-00-00",
        "duration_(hours)": 3,
        "event_category": "maintenance schedule",
        "area_affected": {
            "ALAKNANDA": [
                "40-BLOCK CR PARK"
            ]
        }
    },
    {
        "country": "India",
        "start": "2025-03-17_11-00-00",
        "end": "2025-03-17_14-00-00",
        "duration_(hours)": 3,
        "event_category": "maintenance schedule",
        "area_affected": {
            "NANGLOI": [
                "VIRAT APARTMENT PASCHIM VIHAR",
                "BLOCK C JAWALAPURI PASCHIM VIHAR",
                "BLOCK S JAWALAPURI EXTENSION PASCHIM VIHAR",
                "CAMP 5 JAWALAPURI PASCHIM VIHAR"
            ]
        }
    },
    {
        "country": "India",
        "start": "2025-03-17_11-00-00",
        "end": "2025-03-17_14-00-00",
        "duration_(hours)": 3,
        "event_category": "maintenance schedule",
        "area_affected": {
            "CHHATARPUR": [
                "ANSAL VILLAS SAT BARI",
                "FATEHPUR BERI",
                "CHANDAN HOLA",
                "ASOLA"
            ]
        }
    },
    {
        "country": "India",
        "start": "2025-03-17_11-00-00",
        "end": "2025-03-17_14-00-00",
        "duration_(hours)": 3,
        "event_category": "maintenance schedule",
        "area_affected": {
            "PALAM": [
                "SECR 8 DWARKA",
                "BLOCK P RAJ NAGAR EXTENSION RAJ NAGAR"
            ]
        }
    },
    {
        "country": "India",
        "start": "2025-03-17_11-00-00",
        "end": "2025-03-17_14-00-00",
        "duration_(hours)": 3,
        "event_category": "maintenance schedule",
        "area_affected": {
            "JAFFARPUR": [
                "ISSAPUR VILLAGE",
                "BAQAR GARH VILLAGE",
                "BADHOSRA",
                "JAFARPUR KALAN VILLAGE",
                "QAZIPUR VILLAGE",
                "MANDHELA KALAN VILLAGE"
            ]
        }
    },
    {
        "country": "India",
        "start": "2025-03-17_11-00-00",
        "end": "2025-03-17_14-00-00",
        "duration_(hours)": 3,
        "event_category": "maintenance schedule",
        "area_affected": {
            "JAFFARPUR": [
                "SHIV VIHAR COLONY GOPAL NAGAR NAJAFGARH",
                "HAIBUTPURA EXTENSION HAIBUTPUR",
                "SARSWATI ENCLAVE GOPAL NAGAR NAJAFGARH",
                "HAIBUTPUR"
            ]
        }
    },
    {
        "country": "India",
        "start": "2025-03-17_11-00-00",
        "end": "2025-03-17_14-00-00",
        "duration_(hours)": 3,
        "event_category": "maintenance schedule",
        "area_affected": {
            "R K PURAM": [
                "WEST BLOCK RAMAKRISHNA PURAM"
            ]
        }
    },
    {
        "country": "India",
        "start": "2025-03-17_10-00-00",
        "end": "2025-03-17_13-00-00",
        "duration_(hours)": 3,
        "event_category": "maintenance schedule",
        "area_affected": {
            "SAKET": [
                "BLOCK J SAKET"
            ]
        }
    },
    {
        "country": "India",
        "start": "2025-03-17_10-00-00",
        "end": "2025-03-17_13-00-00",
        "duration_(hours)": 3,
        "event_category": "maintenance schedule",
        "area_affected": {
            "VASANT KUNJ": [
                "B-8 V. KUNJ (VIA GOINKA SCHOOL"
            ]
        }
    },
    {
        "country": "India",
        "start": "2025-03-17_10-00-00",
        "end": "2025-03-17_13-00-00",
        "duration_(hours)": 3,
        "event_category": "maintenance schedule",
        "area_affected": {
            "DWARKA": [
                "BHARAT VIHAR DWARKA"
            ]
        }
    },
    {
        "country": "India",
        "start": "2025-03-17_10-00-00",
        "end": "2025-03-17_13-00-00",
        "duration_(hours)": 3,
        "event_category": "maintenance schedule",
        "area_affected": {
            "NAJAFGARH": [
                "BLOCK D LAXMI VIHAR COLONY NANGLI SAKRAWATI"
            ]
        }
    },
    {
        "country": "India",
        "start": "2025-03-17_10-00-00",
        "end": "2025-03-17_13-00-00",
        "duration_(hours)": 3,
        "event_category": "maintenance schedule",
        "area_affected": {
            "PUNJABI BAGH": [
                "JANTA COLONY PASCHIM VIHAR"
            ]
        }
    },
    {
        "country": "India",
        "start": "2025-03-17_10-00-00",
        "end": "2025-03-17_13-00-00",
        "duration_(hours)": 3,
        "event_category": "maintenance schedule",
        "area_affected": {
            "PUNJABI BAGH": [
                "NEW MULTAN NAGAR SHAKURBASTI"
            ]
        }
    },
    {
        "country": "India",
        "start": "2025-03-17_10-00-00",
        "end": "2025-03-17_13-00-00",
        "duration_(hours)": 3,
        "event_category": "maintenance schedule",
        "area_affected": {
            "SAKET": [
                "BLOCK E PARYAVARAN COMPLEX SAINIK FARM",
                "BLOCK C PARYAVARAN COMPLEX SAINIK FARM",
                "BLOCK A PARYAVARAN COMPLEX SAINIK FARM",
                "FREEDOM FIGHTER VIHAR SAINIK FARM",
                "BLOCK D PARYAVARAN COMPLEX SAINIK FARM"
            ]
        }
    },
    {
        "country": "India",
        "start": "2025-03-17_10-00-00",
        "end": "2025-03-17_13-00-00",
        "duration_(hours)": 3,
        "event_category": "maintenance schedule",
        "area_affected": {
            "NAJAFGARH": [
                "KHARKHARI NAHA VILLAGE",
                "PIND WALA KALAN VILLAGE"
            ]
        }
    },
    {
        "country": "India",
        "start": "2025-03-17_10-00-00",
        "end": "2025-03-17_13-00-00",
        "duration_(hours)": 3,
        "event_category": "maintenance schedule",
        "area_affected": {
            "VASANT KUNJ": [
                "SAMALKA"
            ]
        }
    },
    {
        "country": "India",
        "start": "2025-03-17_10-00-00",
        "end": "2025-03-17_13-00-00",
        "duration_(hours)": 3,
        "event_category": "maintenance schedule",
        "area_affected": {
            "NAJAFGARH": [
                "BLOCK E NEW ROSHAN PURA NAJAFGARH",
                "DURGA PARK NAJAFGARH",
                "BLOCK Q NEW ROSHAN PURA NAJAFGARH"
            ]
        }
    },
    {
        "country": "India",
        "start": "2025-03-17_10-00-00",
        "end": "2025-03-17_13-00-00",
        "duration_(hours)": 3,
        "event_category": "maintenance schedule",
        "area_affected": {
            "NAJAFGARH": [
                "NANAK HERI VILLAGE",
                "CHAWLA",
                "RAGHOPUR VILLAGE"
            ]
        }
    },
    {
        "country": "India",
        "start": "2025-03-17_10-00-00",
        "end": "2025-03-17_13-00-00",
        "duration_(hours)": 3,
        "event_category": "maintenance schedule",
        "area_affected": {
            "MOHAN GARDEN": [
                "BLOCK B SEWAK PARK DWARKA"
            ]
        }
    },
    {
        "country": "India",
        "start": "2025-03-17_10-00-00",
        "end": "2025-03-17_13-00-00",
        "duration_(hours)": 3,
        "event_category": "maintenance schedule",
        "area_affected": {
            "JANAKPURI": [
                "A-15 MAYAPUR"
            ]
        }
    },
    {
        "country": "India",
        "start": "2025-03-17_10-00-00",
        "end": "2025-03-17_13-00-00",
        "duration_(hours)": 3,
        "event_category": "maintenance schedule",
        "area_affected": {
            "TAGORE GARDEN": [
                "BLOCK B PRITHVI PARK TILAK NAGAR"
            ]
        }
    },
    {
        "country": "India",
        "start": "2025-03-17_10-00-00",
        "end": "2025-03-17_13-00-00",
        "duration_(hours)": 3,
        "event_category": "maintenance schedule",
        "area_affected": {
            "NEHRU PLACE": [
                "BLOCK Q LAJPAT NAGAR IV LAJPAT NAGAR"
            ]
        }
    },
    {
        "country": "India",
        "start": "2025-03-17_10-00-00",
        "end": "2025-03-17_13-00-00",
        "duration_(hours)": 3,
        "event_category": "maintenance schedule",
        "area_affected": {
            "DWARKA": [
                "SECR 18B DWARKA"
            ]
        }
    },
    {
        "country": "India",
        "start": "2025-03-17_10-00-00",
        "end": "2025-03-17_13-00-00",
        "duration_(hours)": 3,
        "event_category": "maintenance schedule",
        "area_affected": {
            "NAJAFGARH": [
                "KHAIRA VILLAGE",
                "KHARKHARI NAHA VILLAGE",
                "PAPRAWAT VILLAGE",
                "PREM NAGAR PAPRAWAT VILLAGE",
                "DURGA VIHAR II DINPUR",
                "DURGA VIHAR I DINPUR",
                "SHYAM ENCLAVE DINPUR",
                "BLOCK E SHYAM VIHAR I NAJAFGARH"
            ]
        }
    },
    {
        "country": "India",
        "start": "2025-03-17_11-00-00",
        "end": "2025-03-17_16-00-00",
        "duration_(hours)": 5,
        "event_category": "maintenance schedule",
        "area_affected": {
            "VASANT KUNJ": [
                "GHITORNI VILLAGE GHITORNI"
            ]
        }
    },
    {
        "country": "India",
        "start": "2025-03-17_11-00-00",
        "end": "2025-03-17_16-00-00",
        "duration_(hours)": 5,
        "event_category": "maintenance schedule",
        "area_affected": {
            "VASANT KUNJ": [
                "KISHANGARH VILLAGE SECTOR A VASANT KUNJ"
            ]
        }
    },
    {
        "country": "India",
        "start": "2025-03-17_11-00-00",
        "end": "2025-03-17_15-00-00",
        "duration_(hours)": 4,
        "event_category": "maintenance schedule",
        "area_affected": {
            "VASANT KUNJ": [
                "SHAHABAD MUHAMMADPUR VILLAGE DWARKA"
            ]
        }
    },
    {
        "country": "India",
        "start": "2025-03-17_10-00-00",
        "end": "2025-03-17_14-00-00",
        "duration_(hours)": 4,
        "event_category": "maintenance schedule",
        "area_affected": {
            "VASANT KUNJ": [
                "SAMALKA"
            ]
        }
    }
]